{
  "title": "List item pattern 01",
  "slug": "list-item-pattern-01",
  "hero_snippet": "lp01-hero",
  "beta": true,
  "soon": true,
  "summary": "List item pattern 01 is built on top of the base list and list item components and supports slot-based composition for flexible layouts and supports interactive row behavior.",
  "preamble": "List item pattern 01 provides a ready-to-use row structure for displaying labels and values with support for selection, navigation, and row-level actions. Use the lead, main, and trail slots to combine icons, text and actions. This ensures consistent layout, spacing, and accessibility while allowing flexibility through slots.",
  "anatomy": false,
  "category": [
    "Patterns"
  ],
  "platform": {
    "web": false,
    "ios": false,
    "android": false
  },
  "overview": [
    {
      "title": "Items",
      "tag": "H2",
      "section-content": "Use items property to get predefined styling for 2-3 columns.\n\nNote: Use custom content directly in the row to be slotted into main, if you want to show more columns.",
      "cols": "2"
    },
    {
      "title": "Interaction",
      "tag": "H2",
      "cols": "2",
      "columns": [
        {
          "type": "rich-text",
          "title": "Selectable",
          "tag": "H3",
          "content": "Enable `selectable` to show a checkbox and support checked/unchecked states."
        },
        {
          "type": "snippet",
          "plain": false,
          "replay": false,
          "Snippet": "lip01-selectable"
        },
        {
          "type": "rich-text",
          "title": "Href",
          "tag": "H3",
          "content": "Add `href` to make the row interactive as a link. Displays a chevron in the trail slot."
        },
        {
          "type": "snippet",
          "plain": false,
          "replay": false,
          "Snippet": "lip01-href"
        },
        {
          "type": "rich-text",
          "title": "Selectable with href",
          "tag": "H3",
          "content": "Combine checkbox selection and link navigation in the same row."
        },
        {
          "type": "snippet",
          "plain": false,
          "replay": false,
          "Snippet": "lip01-selectable-href"
        }
      ]
    },
    {
      "title": "Padding inline",
      "section-content": "Use the `padding-inline` property to customize horizontal padding on a list item. Set to `0` to remove padding. Defaults to `s`.",
      "cols": "2",
      "columns": [
        {
          "type": "rich-text",
          "title": "Custom padding-inline",
          "tag": "H3"
        },
        {
          "type": "snippet",
          "plain": false,
          "replay": false,
          "Snippet": "lip01-padding-inline-custom"
        },
        {
          "type": "rich-text",
          "title": "No padding-inline",
          "tag": "H3"
        },
        {
          "type": "snippet",
          "plain": false,
          "replay": false,
          "Snippet": "lip01-no-padding-inline"
        }
      ]
    },
    {
      "title": "Slots",
      "section-content": "List item pattern 01 is built on top of the base list and list item components and supports slot-based composition for flexible layouts and interactions.",
      "cols": "1"
    },
    {
      "title": "Lead slot",
      "tag": "H3",
      "section-content": "Use for icons, avatars, or custom leading content. When `selectable` is enabled, it shows a checkbox.",
      "cols": "3",
      "columns": [
        {
          "type": "snippet",
          "plain": false,
          "replay": false,
          "Snippet": "lip01-lead-icon"
        },
        {
          "type": "snippet",
          "plain": false,
          "replay": false,
          "Snippet": "lip01-lead-avatar"
        },
        {
          "type": "snippet",
          "plain": false,
          "replay": false,
          "Snippet": "lip01-lead-badge"
        }
      ]
    },
    {
      "title": "Main",
      "tag": "H3",
      "section-content": "Use custom content directly in the row.",
      "cols": "2",
      "columns": [
        {
          "type": "snippet",
          "plain": false,
          "replay": false,
          "Snippet": "lip01-main-text"
        },
        {
          "type": "snippet",
          "plain": false,
          "replay": false,
          "Snippet": "lip01-main-custom"
        }
      ]
    },
    {
      "title": "Trail slot",
      "tag": "H3",
      "section-content": "Use for actions such as links or buttons. When `href` is set, the row renders a chevron link in the trail."
    }
  ]
}